fanfou_client.py
main.py
fanfou_mcp-0.1.1.dist-info/METADATA
fanfou_mcp-0.1.1.dist-info/WHEEL
fanfou_mcp-0.1.1.dist-info/entry_points.txt
fanfou_mcp-0.1.1.dist-info/licenses/LICENSE
fanfou_mcp-0.1.1.dist-info/RECORD
