Metadata-Version: 2.4
Name: fanfou-mcp
Version: 0.1.1
Summary: 饭否 MCP 服务器 - 基于 FastMCP 构建的饭否（Fanfou）MCP 服务器
Project-URL: Homepage, https://github.com/kingcos/fanfou-mcp
Project-URL: Repository, https://github.com/kingcos/fanfou-mcp
Project-URL: Issues, https://github.com/kingcos/fanfou-mcp/issues
Project-URL: Documentation, https://github.com/kingcos/fanfou-mcp/blob/main/docs/API.md
Author-email: kingcos <kingcos@foxmail.com>
License: MIT License
License-File: LICENSE
Keywords: fanfou,mcp,model-context-protocol,social-media
Classifier: Development Status :: 3 - Alpha
Classifier: Intended Audience :: Developers
Classifier: License :: OSI Approved :: MIT License
Classifier: Programming Language :: Python :: 3
Classifier: Programming Language :: Python :: 3.11
Classifier: Programming Language :: Python :: 3.12
Classifier: Topic :: Communications :: Chat
Classifier: Topic :: Internet :: WWW/HTTP :: Dynamic Content
Classifier: Topic :: Software Development :: Libraries :: Python Modules
Requires-Python: >=3.11
Requires-Dist: fastmcp>=2.10.5
Requires-Dist: oauth2>=1.9.0.post1
Requires-Dist: requests>=2.32.4
Requires-Dist: twine>=5.0.0
